{
  "fixture_id": "R32_3",
  "home": "Germany",
  "away": "Paraguay",
  "home_multiplier": 1.0,
  "away_multiplier": 1.0,
  "notes": "Germany are without CB Nico Schlotterbeck (knee ligament injury, tournament over) and LB Nathaniel Brown is a late fitness doubt (adductor) though Nagelsmann expects him to play; Paraguay are missing suspended MF Diego Gómez and CB Omar Alderete is doubtful (knee), while Almiron returns after serving his one-match ban for the red card vs Turkey.",
  "home_scorers": [
    "Kai Havertz (starting striker, focal point of attack)",
    "Jamal Musiala (creative No.10, high goal involvement)",
    "Florian Wirtz (attacking midfielder, set-piece threat)"
  ],
  "away_scorers": [
    "Antonio Sanabria (lone striker, Paraguay's primary finisher)",
    "Julio Enciso (dynamic forward, direct goal threat)",
    "Miguel Almiron (returning attacker, energetic runner into box)"
  ],
  "source": "lineup_fetch",
  "fetched_at": "2026-06-29T20:32:05.400406+00:00",
  "lineup_home_absent": 0,
  "lineup_away_absent": 0
}